{
  "id": "mirai-light",
  "name": "Mirai Light",
  "author": "Mirai",
  "version": "1.0.0",
  "type": "light",
  "colors": {
    "editor.background": "#FFFFFF",
    "editor.foreground": "#111827",
    "sideBar.background": "#EEF2F7",
    "sideBar.foreground": "#111827",
    "activityBar.background": "#F6F8FB",
    "activityBar.foreground": "#111827",
    "titleBar.activeBackground": "#F6F8FB",
    "titleBar.activeForeground": "#111827",
    "statusBar.background": "#EEF2F7",
    "statusBar.foreground": "#111827",
    "focusBorder": "#4F46E5",
    "foreground": "#111827",
    "widget.shadow": "rgba(0, 0, 0, 0.05)",
    "panel.background": "#EEF2F7",
    "tab.activeBackground": "#FFFFFF",
    "tab.inactiveBackground": "#EEF2F7",
    "tab.activeForeground": "#111827",
    "terminal.background": "#FFFFFF",
    "terminal.foreground": "#111827",
    "terminal.ansiBlack": "#111827",
    "terminal.ansiRed": "#EF4444",
    "terminal.ansiGreen": "#10B981",
    "terminal.ansiYellow": "#F59E0B",
    "terminal.ansiBlue": "#4F46E5",
    "terminal.ansiMagenta": "#7C3AED",
    "terminal.ansiCyan": "#06B6D4",
    "terminal.ansiWhite": "#6B7280",
    "terminal.ansiBrightBlack": "#6B7280",
    "terminal.ansiBrightRed": "#FCA5A5",
    "terminal.ansiBrightGreen": "#6EE7B7",
    "terminal.ansiBrightYellow": "#FCD34D",
    "terminal.ansiBrightBlue": "#93C5FD",
    "terminal.ansiBrightMagenta": "#C4B5FD",
    "terminal.ansiBrightCyan": "#67E8F9",
    "terminal.ansiBrightWhite": "#DCE3ED"
  }
}
